state_machine_semaphore/__init__.py
state_machine_semaphore/py.typed
state_machine_semaphore/_jsii/__init__.py
state_machine_semaphore/_jsii/state-machine-semaphore@0.1.583.jsii.tgz
state_machine_semaphore-0.1.583.dist-info/LICENSE
state_machine_semaphore-0.1.583.dist-info/METADATA
state_machine_semaphore-0.1.583.dist-info/WHEEL
state_machine_semaphore-0.1.583.dist-info/top_level.txt
state_machine_semaphore-0.1.583.dist-info/RECORD
