Metadata-Version: 2.1
Name: state-machine-semaphore
Version: 0.1.583
Summary: Create distributed semaphores using AWS Step Functions and Amazon DynamoDB to control concurrent invocations of contentious work.
Home-page: https://github.com/dontirun/state-machine-semaphore.git
Author: Arun Donti<dontirun@gmail.com>
License: Apache-2.0
Project-URL: Source, https://github.com/dontirun/state-machine-semaphore.git
Classifier: Intended Audience :: Developers
Classifier: Operating System :: OS Independent
Classifier: Programming Language :: JavaScript
Classifier: Programming Language :: Python :: 3 :: Only
Classifier: Programming Language :: Python :: 3.8
Classifier: Programming Language :: Python :: 3.9
Classifier: Programming Language :: Python :: 3.10
Classifier: Programming Language :: Python :: 3.11
Classifier: Typing :: Typed
Classifier: Development Status :: 5 - Production/Stable
Classifier: License :: OSI Approved
Requires-Python: ~=3.8
License-File: LICENSE
Requires-Dist: aws-cdk-lib <3.0.0,>=2.22.0
Requires-Dist: constructs <11.0.0,>=10.0.5
Requires-Dist: jsii <2.0.0,>=1.97.0
Requires-Dist: publication >=0.0.3
Requires-Dist: typeguard ~=2.13.3
